{
"tableData3":[
          {
            "juese":"管理员",
            "yonghu":"王管理"
          },
            {
            "juese":"医生",
            "yonghu":"刘利伟 何颖成 黄洪峰 黄振华 胡苏 梁景炜 李辉 刘林 刘易林 李耀明 王展鹏 温智光 林水运 杨超峰 杨楚新 杨海裕 钟南"
            
          },
          {
            "juese":"药师",
            "yonghu":"刘利伟 何颖成 黄洪峰 黄振华 胡苏 梁景炜 李辉 刘林 刘易林 李耀明 王展鹏 温智光"
            
          },
          {
           "juese":"护士",
            "yonghu":"杨楚新 杨海裕 钟南"
            
          },
          {
           "juese":"收费员",
            "yonghu":"松林 吴少萍 吴宗胜 谢凤 张玉婷 周柳莹"
            
          },
          {
            "juese":"财务",
            "yonghu":"谢凤 张玉婷 周柳莹"
            
          }
          ]
}